dogpile_cache_native_redis/__init__.py
dogpile_cache_native_redis/backends.py
dogpile_cache_native_redis-0.1.dist-info/DESCRIPTION.rst
dogpile_cache_native_redis-0.1.dist-info/METADATA
dogpile_cache_native_redis-0.1.dist-info/RECORD
dogpile_cache_native_redis-0.1.dist-info/WHEEL
dogpile_cache_native_redis-0.1.dist-info/entry_points.txt
dogpile_cache_native_redis-0.1.dist-info/metadata.json
dogpile_cache_native_redis-0.1.dist-info/top_level.txt
dogpile_cache_native_redis-0.1.dist-info/zip-safe
