Metadata-Version: 2.0
Name: dogpile-cache-native-redis
Version: 0.1
Summary: backend for dogpile.cache with reading and writing the native value
Home-page: https://github.com/tokibito/dogpile_cache_native_redis
Author: Shinya Okano
Author-email: tokibito@gmail.com
License: MIT
Keywords: caching
Platform: UNKNOWN
Classifier: Development Status :: 4 - Beta
Classifier: Intended Audience :: Developers
Classifier: License :: OSI Approved :: MIT License
Classifier: Programming Language :: Python
Classifier: Programming Language :: Python :: 3
